fetchin/__init__.py
fetchin/fetcher/__init__.py
fetchin/fetcher/fetcher.py
fetchin/logging/__init__.py
fetchin/logging/logger.py
fetchin/metrics/__init__.py
fetchin/metrics/metrics_interface.py
fetchin/metrics/prometheus_metrics.py
fetchin-0.1.1.dist-info/LICENSE
fetchin-0.1.1.dist-info/METADATA
fetchin-0.1.1.dist-info/WHEEL
fetchin-0.1.1.dist-info/top_level.txt
fetchin-0.1.1.dist-info/RECORD
