Metadata-Version: 2.1
Name: fetchin
Version: 0.1.1
Summary: Library for handling HTTP requests with circuit breaker, logs, and metrics.
Author: Rômulo Freires
License: MIT
Classifier: Programming Language :: Python :: 3
Classifier: License :: OSI Approved :: MIT License
Classifier: Operating System :: OS Independent
Requires-Python: >=3.6
License-File: LICENSE
Requires-Dist: requests==2.32.3
Requires-Dist: pybreaker==1.2.0
Requires-Dist: prometheus-client==0.20.0
Provides-Extra: dev
Requires-Dist: black; extra == "dev"
Requires-Dist: flake8; extra == "dev"
Requires-Dist: pytest; extra == "dev"
